{
    "partylist": [
        {
            "addressType": "DEFAULT_SENDER",
            "partyId": "1040",
            "user": {
                "uid": 1002,
                "acceptedTCFlag": "F"
            },
            "contact": {
                "personName": "asdfdas",
                "companyName": null,
                "phoneNumber": "1234123",
                "phoneExtension": null,
                "emailAddress": "aaq@q.in",
                "passportNo": null,
                "taxId": null
            },
            "address": {
                "streetlines": [
                    "asdfas"
                ],
                "city": "A KUNG KOK",
                "stateOrProvinceCode": null,
                "postalCode": null,
                "countryCode": "HK",
                "residential": false,
                "visitor": false
            }
        }
    ]
}